[{"post_num": 35, "unique_id": 25, "click": 17774, "like": 94, "dislike": 47, "name": "SKC코오롱PI", "time": "2018-02-23 16:40"}, {"post_num": 54, "unique_id": 31, "click": 15610, "like": 221, "dislike": 85, "name": "홈캐스트", "time": "2018-02-23 16:40"}, {"post_num": 98, "unique_id": 62, "click": 27802, "like": 77, "dislike": 52, "name": "고려제약", "time": "2018-02-23 16:40"}, {"post_num": 93, "unique_id": 43, "click": 17415, "like": 331, "dislike": 222, "name": "미투온", "time": "2018-02-23 16:40"}, {"post_num": 65, "unique_id": 36, "click": 17330, "like": 176, "dislike": 58, "name": "한화테크윈", "time": "2018-02-23 16:40"}, {"post_num": 44, "unique_id": 29, "click": 17696, "like": 133, "dislike": 79, "name": "EMW", "time": "2018-02-23 16:40"}, {"post_num": 33, "unique_id": 25, "click": 20662, "like": 247, "dislike": 56, "name": "삼성물산", "time": "2018-02-23 16:40"}, {"post_num": 27, "unique_id": 21, "click": 16285, "like": 69, "dislike": 22, "name": "코스모화학", "time": "2018-02-23 16:40"}, {"post_num": 5, "unique_id": 5, "click": 2082, "like": 15, "dislike": 11, "name": "레고켐바이오", "time": "2018-02-23 16:40"}, {"post_num": 8, "unique_id": 6, "click": 1530, "like": 8, "dislike": 15, "name": "KG이니시스", "time": "2018-02-23 16:40"}, {"post_num": 67, "unique_id": 45, "click": 21909, "like": 384, "dislike": 89, "name": "JYP Ent.", "time": "2018-02-23 16:40"}, {"post_num": 12, "unique_id": 11, "click": 2498, "like": 45, "dislike": 38, "name": "씨에스윈드", "time": "2018-02-23 16:40"}, {"post_num": 3, "unique_id": 3, "click": 597, "like": 11, "dislike": 2, "name": "KG모빌리언스", "time": "2018-02-23 16:40"}, {"post_num": 6, "unique_id": 3, "click": 2311, "like": 5, "dislike": 6, "name": "삼성생명", "time": "2018-02-23 16:40"}, {"post_num": 64, "unique_id": 40, "click": 18267, "like": 152, "dislike": 77, "name": "셀루메드", "time": "2018-02-23 16:40"}, {"post_num": 32, "unique_id": 12, "click": 6843, "like": 34, "dislike": 17, "name": "대한항공", "time": "2018-02-23 16:40"}, {"post_num": 24, "unique_id": 16, "click": 9863, "like": 79, "dislike": 64, "name": "롯데지주", "time": "2018-02-23 16:40"}, {"post_num": 51, "unique_id": 36, "click": 26073, "like": 76, "dislike": 34, "name": "AP시스템", "time": "2018-02-23 16:40"}, {"post_num": 12, "unique_id": 12, "click": 3788, "like": 54, "dislike": 13, "name": "휘닉스소재", "time": "2018-02-23 16:40"}, {"post_num": 176, "unique_id": 81, "click": 44030, "like": 179, "dislike": 247, "name": "SBI인베스트먼트", "time": "2018-02-23 16:40"}, {"post_num": 6, "unique_id": 6, "click": 2547, "like": 13, "dislike": 14, "name": "메디톡스", "time": "2018-02-23 16:40"}, {"post_num": 39, "unique_id": 23, "click": 9432, "like": 41, "dislike": 19, "name": "씨트리", "time": "2018-02-23 16:40"}, {"post_num": 0, "unique_id": 0, "click": 0, "like": 0, "dislike": 0, "name": "이크레더블", "time": "2018-02-23 16:40"}, {"post_num": 8, "unique_id": 7, "click": 2901, "like": 19, "dislike": 5, "name": "현대제철", "time": "2018-02-23 16:40"}, {"post_num": 94, "unique_id": 56, "click": 46508, "like": 402, "dislike": 107, "name": "비에이치", "time": "2018-02-23 16:40"}, {"post_num": 9, "unique_id": 8, "click": 2715, "like": 11, "dislike": 4, "name": "옵트론텍", "time": "2018-02-23 16:40"}, {"post_num": 4, "unique_id": 4, "click": 1446, "like": 13, "dislike": 6, "name": "하림홀딩스", "time": "2018-02-23 16:40"}, {"post_num": 51, "unique_id": 29, "click": 9678, "like": 91, "dislike": 47, "name": "골든센츄리", "time": "2018-02-23 16:40"}, {"post_num": 5, "unique_id": 5, "click": 1892, "like": 33, "dislike": 10, "name": "와이엠티", "time": "2018-02-23 16:40"}, {"post_num": 0, "unique_id": 0, "click": 0, "like": 0, "dislike": 0, "name": "아주캐피탈", "time": "2018-02-23 16:40"}, {"post_num": 6, "unique_id": 6, "click": 2250, "like": 7, "dislike": 9, "name": "현대건설", "time": "2018-02-23 16:40"}, {"post_num": 1, "unique_id": 1, "click": 216, "like": 3, "dislike": 0, "name": "코스메카코리아", "time": "2018-02-23 16:40"}, {"post_num": 2, "unique_id": 2, "click": 167, "like": 0, "dislike": 0, "name": "흥국에프엔비", "time": "2018-02-23 16:40"}, {"post_num": 8, "unique_id": 5, "click": 1044, "like": 5, "dislike": 11, "name": "솔브레인", "time": "2018-02-23 16:40"}, {"post_num": 98, "unique_id": 59, "click": 23684, "like": 123, "dislike": 85, "name": "이디", "time": "2018-02-23 16:40"}, {"post_num": 0, "unique_id": 0, "click": 0, "like": 0, "dislike": 0, "name": "화천기계", "time": "2018-02-23 16:40"}, {"post_num": 13, "unique_id": 10, "click": 2761, "like": 8, "dislike": 9, "name": "알테오젠", "time": "2018-02-23 16:40"}, {"post_num": 3, "unique_id": 3, "click": 316, "like": 6, "dislike": 1, "name": "쿠쿠홀딩스", "time": "2018-02-23 16:40"}, {"post_num": 10, "unique_id": 9, "click": 2400, "like": 16, "dislike": 9, "name": "화진", "time": "2018-02-23 16:40"}, {"post_num": 3, "unique_id": 3, "click": 576, "like": 5, "dislike": 0, "name": "대신증권", "time": "2018-02-23 16:40"}, {"post_num": 7, "unique_id": 2, "click": 598, "like": 1, "dislike": 4, "name": "차이나그레이트", "time": "2018-02-23 16:40"}, {"post_num": 70, "unique_id": 40, "click": 20640, "like": 156, "dislike": 63, "name": "시큐브", "time": "2018-02-23 16:40"}, {"post_num": 12, "unique_id": 12, "click": 5460, "like": 19, "dislike": 9, "name": "에코프로", "time": "2018-02-23 16:40"}, {"post_num": 3, "unique_id": 3, "click": 1945, "like": 9, "dislike": 25, "name": "씨씨에스", "time": "2018-02-23 16:40"}, {"post_num": 4, "unique_id": 4, "click": 794, "like": 3, "dislike": 0, "name": "감마누", "time": "2018-02-23 16:40"}, {"post_num": 17, "unique_id": 11, "click": 4519, "like": 60, "dislike": 10, "name": "코오롱생명과학", "time": "2018-02-23 16:40"}, {"post_num": 47, "unique_id": 21, "click": 9382, "like": 50, "dislike": 68, "name": "엘컴텍", "time": "2018-02-23 16:40"}, {"post_num": 0, "unique_id": 0, "click": 0, "like": 0, "dislike": 0, "name": "아세아제지", "time": "2018-02-23 16:40"}, {"post_num": 18, "unique_id": 14, "click": 5234, "like": 79, "dislike": 19, "name": "드림시큐리티", "time": "2018-02-23 16:40"}, {"post_num": 1, "unique_id": 1, "click": 134, "like": 0, "dislike": 0, "name": "고영", "time": "2018-02-23 16:40"}, {"post_num": 2, "unique_id": 2, "click": 645, "like": 2, "dislike": 3, "name": "이엠텍", "time": "2018-02-23 16:40"}, {"post_num": 0, "unique_id": 0, "click": 0, "like": 0, "dislike": 0, "name": "SIMPAC Metal", "time": "2018-02-23 16:40"}, {"post_num": 0, "unique_id": 0, "click": 0, "like": 0, "dislike": 0, "name": "펩트론", "time": "2018-02-23 16:40"}, {"post_num": 2, "unique_id": 2, "click": 149, "like": 1, "dislike": 0, "name": "인터로조", "time": "2018-02-23 16:40"}, {"post_num": 0, "unique_id": 0, "click": 0, "like": 0, "dislike": 0, "name": "디지아이", "time": "2018-02-23 16:40"}, {"post_num": 5, "unique_id": 5, "click": 1123, "like": 1, "dislike": 3, "name": "원익", "time": "2018-02-23 16:40"}, {"post_num": 1, "unique_id": 1, "click": 45, "like": 0, "dislike": 0, "name": "세아베스틸", "time": "2018-02-23 16:40"}, {"post_num": 16, "unique_id": 13, "click": 3441, "like": 34, "dislike": 14, "name": "코오롱인더", "time": "2018-02-23 16:40"}, {"post_num": 11, "unique_id": 7, "click": 5823, "like": 50, "dislike": 78, "name": "대화제약", "time": "2018-02-23 16:40"}, {"post_num": 3, "unique_id": 2, "click": 1250, "like": 1, "dislike": 8, "name": "경남제약", "time": "2018-02-23 16:40"}, {"post_num": 6, "unique_id": 5, "click": 1850, "like": 20, "dislike": 29, "name": "라온시큐어", "time": "2018-02-23 16:40"}, {"post_num": 1, "unique_id": 1, "click": 77, "like": 3, "dislike": 0, "name": "NICE", "time": "2018-02-23 16:40"}, {"post_num": 1, "unique_id": 1, "click": 99, "like": 0, "dislike": 2, "name": "동방", "time": "2018-02-23 16:40"}, {"post_num": 6, "unique_id": 6, "click": 860, "like": 5, "dislike": 3, "name": "SG", "time": "2018-02-23 16:40"}, {"post_num": 5, "unique_id": 5, "click": 585, "like": 2, "dislike": 3, "name": "미스터블루", "time": "2018-02-23 16:40"}, {"post_num": 35, "unique_id": 25, "click": 13244, "like": 71, "dislike": 33, "name": "사파이어테크놀로지", "time": "2018-02-23 16:40"}, {"post_num": 1, "unique_id": 1, "click": 167, "like": 1, "dislike": 1, "name": "조선선재", "time": "2018-02-23 16:40"}, {"post_num": 4, "unique_id": 4, "click": 172, "like": 0, "dislike": 1, "name": "한창산업", "time": "2018-02-23 16:40"}, {"post_num": 27, "unique_id": 14, "click": 5387, "like": 31, "dislike": 23, "name": "대봉엘에스", "time": "2018-02-23 16:40"}, {"post_num": 28, "unique_id": 10, "click": 7380, "like": 81, "dislike": 84, "name": "대웅제약", "time": "2018-02-23 16:40"}, {"post_num": 3, "unique_id": 3, "click": 1425, "like": 20, "dislike": 0, "name": "키이스트", "time": "2018-02-23 16:40"}, {"post_num": 0, "unique_id": 0, "click": 0, "like": 0, "dislike": 0, "name": "에코플라스틱", "time": "2018-02-23 16:40"}, {"post_num": 12, "unique_id": 9, "click": 3198, "like": 28, "dislike": 11, "name": "성도이엔지", "time": "2018-02-23 16:40"}, {"post_num": 5, "unique_id": 5, "click": 787, "like": 0, "dislike": 1, "name": "삼일", "time": "2018-02-23 16:40"}, {"post_num": 2, "unique_id": 2, "click": 102, "like": 0, "dislike": 0, "name": "대진디엠피", "time": "2018-02-23 16:40"}, {"post_num": 0, "unique_id": 0, "click": 0, "like": 0, "dislike": 0, "name": "웰크론한텍", "time": "2018-02-23 16:40"}, {"post_num": 1, "unique_id": 1, "click": 77, "like": 1, "dislike": 0, "name": "CJ오쇼핑", "time": "2018-02-23 16:40"}, {"post_num": 2, "unique_id": 2, "click": 726, "like": 2, "dislike": 9, "name": "더존비즈온", "time": "2018-02-23 16:40"}, {"post_num": 0, "unique_id": 0, "click": 0, "like": 0, "dislike": 0, "name": "인화정공", "time": "2018-02-23 16:40"}, {"post_num": 3, "unique_id": 3, "click": 863, "like": 2, "dislike": 11, "name": "맥쿼리인프라", "time": "2018-02-23 16:40"}, {"post_num": 5, "unique_id": 2, "click": 1432, "like": 4, "dislike": 12, "name": "이상네트웍스", "time": "2018-02-23 16:40"}, {"post_num": 0, "unique_id": 0, "click": 0, "like": 0, "dislike": 0, "name": "엘엠에스", "time": "2018-02-23 16:40"}, {"post_num": 1, "unique_id": 1, "click": 63, "like": 0, "dislike": 0, "name": "멕아이씨에스", "time": "2018-02-23 16:40"}, {"post_num": 0, "unique_id": 0, "click": 0, "like": 0, "dislike": 0, "name": "하이록코리아", "time": "2018-02-23 16:40"}, {"post_num": 1, "unique_id": 1, "click": 61, "like": 0, "dislike": 0, "name": "이씨에스", "time": "2018-02-23 16:40"}, {"post_num": 1, "unique_id": 1, "click": 37, "like": 0, "dislike": 0, "name": "화성밸브", "time": "2018-02-23 16:40"}, {"post_num": 6, "unique_id": 5, "click": 1031, "like": 5, "dislike": 2, "name": "애경유화", "time": "2018-02-23 16:40"}, {"post_num": 11, "unique_id": 9, "click": 4265, "like": 26, "dislike": 33, "name": "안트로젠", "time": "2018-02-23 16:40"}, {"post_num": 10, "unique_id": 10, "click": 6165, "like": 16, "dislike": 10, "name": "에이디칩스", "time": "2018-02-23 16:40"}, {"post_num": 30, "unique_id": 12, "click": 3638, "like": 49, "dislike": 23, "name": "삼영엠텍", "time": "2018-02-23 16:40"}, {"post_num": 33, "unique_id": 22, "click": 14780, "like": 107, "dislike": 103, "name": "대우건설", "time": "2018-02-23 16:40"}, {"post_num": 0, "unique_id": 0, "click": 0, "like": 0, "dislike": 0, "name": "세아특수강", "time": "2018-02-23 16:40"}, {"post_num": 6, "unique_id": 6, "click": 2779, "like": 25, "dislike": 6, "name": "CJ", "time": "2018-02-23 16:40"}, {"post_num": 5, "unique_id": 4, "click": 561, "like": 6, "dislike": 8, "name": "엔에스", "time": "2018-02-23 16:40"}, {"post_num": 2, "unique_id": 2, "click": 121, "like": 0, "dislike": 0, "name": "네오오토", "time": "2018-02-23 16:40"}, {"post_num": 8, "unique_id": 6, "click": 1112, "like": 9, "dislike": 13, "name": "아비스타", "time": "2018-02-23 16:40"}, {"post_num": 3, "unique_id": 3, "click": 166, "like": 0, "dislike": 0, "name": "캐스텍코리아", "time": "2018-02-23 16:40"}, {"post_num": 66, "unique_id": 33, "click": 39672, "like": 370, "dislike": 214, "name": "에이치엘비생명과학", "time": "2018-02-23 16:40"}, {"post_num": 0, "unique_id": 0, "click": 0, "like": 0, "dislike": 0, "name": "S&T모티브", "time": "2018-02-23 16:40"}]