[{"post_num": 13, "unique_id": 12, "click": 4397, "like": 20, "dislike": 23, "name": "두산중공업", "time": "2018-02-28 14:00"}, {"post_num": 122, "unique_id": 67, "click": 39438, "like": 335, "dislike": 113, "name": "한미약품", "time": "2018-02-28 14:00"}, {"post_num": 32, "unique_id": 22, "click": 9284, "like": 56, "dislike": 32, "name": "대한항공", "time": "2018-02-28 14:00"}, {"post_num": 75, "unique_id": 50, "click": 16513, "like": 238, "dislike": 48, "name": "용평리조트", "time": "2018-02-28 14:00"}, {"post_num": 19, "unique_id": 13, "click": 7477, "like": 31, "dislike": 18, "name": "알서포트", "time": "2018-02-28 14:00"}, {"post_num": 6, "unique_id": 5, "click": 852, "like": 1, "dislike": 0, "name": "서진시스템", "time": "2018-02-28 14:00"}, {"post_num": 45, "unique_id": 20, "click": 10423, "like": 93, "dislike": 58, "name": "한화테크윈", "time": "2018-02-28 14:00"}, {"post_num": 7, "unique_id": 7, "click": 2054, "like": 10, "dislike": 4, "name": "KB금융", "time": "2018-02-28 14:00"}, {"post_num": 5, "unique_id": 5, "click": 2084, "like": 12, "dislike": 3, "name": "이지바이오", "time": "2018-02-28 14:00"}, {"post_num": 0, "unique_id": 0, "click": 0, "like": 0, "dislike": 0, "name": "텔코웨어", "time": "2018-02-28 14:00"}, {"post_num": 16, "unique_id": 13, "click": 6072, "like": 73, "dislike": 55, "name": "대우건설", "time": "2018-02-28 14:00"}, {"post_num": 125, "unique_id": 66, "click": 44743, "like": 440, "dislike": 292, "name": "아남전자", "time": "2018-02-28 14:00"}, {"post_num": 1, "unique_id": 1, "click": 171, "like": 1, "dislike": 0, "name": "한샘", "time": "2018-02-28 14:00"}, {"post_num": 0, "unique_id": 0, "click": 0, "like": 0, "dislike": 0, "name": "인천도시가스", "time": "2018-02-28 14:00"}, {"post_num": 2, "unique_id": 1, "click": 250, "like": 4, "dislike": 0, "name": "뷰웍스", "time": "2018-02-28 14:00"}, {"post_num": 2, "unique_id": 2, "click": 367, "like": 4, "dislike": 3, "name": "브이원텍", "time": "2018-02-28 14:00"}, {"post_num": 4, "unique_id": 4, "click": 943, "like": 16, "dislike": 7, "name": "씨씨에스", "time": "2018-02-28 14:00"}, {"post_num": 3, "unique_id": 3, "click": 498, "like": 4, "dislike": 1, "name": "SKC", "time": "2018-02-28 14:00"}, {"post_num": 44, "unique_id": 26, "click": 7219, "like": 92, "dislike": 76, "name": "다날", "time": "2018-02-28 14:00"}, {"post_num": 1, "unique_id": 1, "click": 8, "like": 0, "dislike": 0, "name": "LG생활건강", "time": "2018-02-28 14:00"}, {"post_num": 6, "unique_id": 4, "click": 733, "like": 4, "dislike": 2, "name": "에코바이오", "time": "2018-02-28 14:00"}, {"post_num": 6, "unique_id": 6, "click": 1212, "like": 9, "dislike": 5, "name": "하이비젼시스템", "time": "2018-02-28 14:00"}, {"post_num": 13, "unique_id": 9, "click": 3730, "like": 16, "dislike": 4, "name": "자화전자", "time": "2018-02-28 14:00"}, {"post_num": 9, "unique_id": 9, "click": 2479, "like": 22, "dislike": 3, "name": "롯데케미칼", "time": "2018-02-28 14:00"}, {"post_num": 16, "unique_id": 14, "click": 8592, "like": 29, "dislike": 32, "name": "대한광통신", "time": "2018-02-28 14:00"}, {"post_num": 3, "unique_id": 3, "click": 969, "like": 4, "dislike": 8, "name": "GS리테일", "time": "2018-02-28 14:00"}, {"post_num": 4, "unique_id": 3, "click": 1112, "like": 8, "dislike": 3, "name": "이녹스첨단소재", "time": "2018-02-28 14:00"}, {"post_num": 0, "unique_id": 0, "click": 0, "like": 0, "dislike": 0, "name": "디와이파워", "time": "2018-02-28 14:00"}, {"post_num": 31, "unique_id": 22, "click": 9232, "like": 115, "dislike": 47, "name": "JYP Ent.", "time": "2018-02-28 14:00"}, {"post_num": 15, "unique_id": 11, "click": 2006, "like": 18, "dislike": 20, "name": "대덕GDS", "time": "2018-02-28 14:00"}, {"post_num": 2, "unique_id": 2, "click": 361, "like": 3, "dislike": 6, "name": "오리온", "time": "2018-02-28 14:00"}, {"post_num": 5, "unique_id": 5, "click": 964, "like": 12, "dislike": 4, "name": "하림", "time": "2018-02-28 14:00"}, {"post_num": 6, "unique_id": 5, "click": 976, "like": 2, "dislike": 7, "name": "NHN한국사이버결제", "time": "2018-02-28 14:00"}, {"post_num": 2, "unique_id": 2, "click": 381, "like": 4, "dislike": 0, "name": "코콤", "time": "2018-02-28 14:00"}, {"post_num": 0, "unique_id": 0, "click": 0, "like": 0, "dislike": 0, "name": "백광소재", "time": "2018-02-28 14:00"}, {"post_num": 0, "unique_id": 0, "click": 0, "like": 0, "dislike": 0, "name": "하이록코리아", "time": "2018-02-28 14:00"}, {"post_num": 15, "unique_id": 10, "click": 6542, "like": 6, "dislike": 25, "name": "현대중공업", "time": "2018-02-28 14:00"}, {"post_num": 2, "unique_id": 2, "click": 626, "like": 11, "dislike": 4, "name": "AP시스템", "time": "2018-02-28 14:00"}, {"post_num": 5, "unique_id": 5, "click": 1672, "like": 12, "dislike": 8, "name": "알테오젠", "time": "2018-02-28 14:00"}, {"post_num": 4, "unique_id": 3, "click": 932, "like": 2, "dislike": 11, "name": "환인제약", "time": "2018-02-28 14:00"}, {"post_num": 0, "unique_id": 0, "click": 0, "like": 0, "dislike": 0, "name": "원일특강", "time": "2018-02-28 14:00"}, {"post_num": 1, "unique_id": 1, "click": 79, "like": 2, "dislike": 2, "name": "LG", "time": "2018-02-28 14:00"}, {"post_num": 35, "unique_id": 20, "click": 6753, "like": 33, "dislike": 19, "name": "배럴", "time": "2018-02-28 14:00"}, {"post_num": 14, "unique_id": 12, "click": 3244, "like": 25, "dislike": 8, "name": "파티게임즈", "time": "2018-02-28 14:00"}, {"post_num": 4, "unique_id": 4, "click": 617, "like": 11, "dislike": 0, "name": "제노포커스", "time": "2018-02-28 14:00"}, {"post_num": 7, "unique_id": 7, "click": 1361, "like": 6, "dislike": 14, "name": "에이티젠", "time": "2018-02-28 14:00"}, {"post_num": 0, "unique_id": 0, "click": 0, "like": 0, "dislike": 0, "name": "한국타이어", "time": "2018-02-28 14:00"}, {"post_num": 22, "unique_id": 17, "click": 8619, "like": 61, "dislike": 29, "name": "팬오션", "time": "2018-02-28 14:00"}, {"post_num": 20, "unique_id": 17, "click": 6157, "like": 46, "dislike": 17, "name": "액션스퀘어", "time": "2018-02-28 14:00"}, {"post_num": 2, "unique_id": 2, "click": 175, "like": 1, "dislike": 1, "name": "케이엠", "time": "2018-02-28 14:00"}, {"post_num": 5, "unique_id": 4, "click": 950, "like": 2, "dislike": 5, "name": "옵트론텍", "time": "2018-02-28 14:00"}, {"post_num": 3, "unique_id": 3, "click": 259, "like": 6, "dislike": 0, "name": "크라운제과", "time": "2018-02-28 14:00"}, {"post_num": 5, "unique_id": 5, "click": 1274, "like": 20, "dislike": 10, "name": "LG하우시스", "time": "2018-02-28 14:00"}, {"post_num": 6, "unique_id": 5, "click": 1545, "like": 15, "dislike": 7, "name": "이엘케이", "time": "2018-02-28 14:00"}, {"post_num": 44, "unique_id": 33, "click": 20910, "like": 62, "dislike": 47, "name": "에코프로", "time": "2018-02-28 14:00"}, {"post_num": 3, "unique_id": 3, "click": 1227, "like": 0, "dislike": 2, "name": "에스티팜", "time": "2018-02-28 14:00"}, {"post_num": 4, "unique_id": 4, "click": 1027, "like": 8, "dislike": 8, "name": "심텍", "time": "2018-02-28 14:00"}, {"post_num": 7, "unique_id": 7, "click": 1672, "like": 14, "dislike": 12, "name": "일진다이아", "time": "2018-02-28 14:00"}, {"post_num": 36, "unique_id": 16, "click": 9402, "like": 75, "dislike": 57, "name": "대웅제약", "time": "2018-02-28 14:00"}, {"post_num": 5, "unique_id": 5, "click": 3313, "like": 32, "dislike": 26, "name": "SK케미칼", "time": "2018-02-28 14:00"}, {"post_num": 4, "unique_id": 3, "click": 353, "like": 6, "dislike": 9, "name": "휴메딕스", "time": "2018-02-28 14:00"}, {"post_num": 20, "unique_id": 14, "click": 6991, "like": 57, "dislike": 16, "name": "아모레퍼시픽", "time": "2018-02-28 14:00"}, {"post_num": 2, "unique_id": 2, "click": 407, "like": 9, "dislike": 4, "name": "동성코퍼레이션", "time": "2018-02-28 14:00"}, {"post_num": 1, "unique_id": 1, "click": 16, "like": 0, "dislike": 0, "name": "태양", "time": "2018-02-28 14:00"}, {"post_num": 0, "unique_id": 0, "click": 0, "like": 0, "dislike": 0, "name": "이건홀딩스", "time": "2018-02-28 14:00"}, {"post_num": 4, "unique_id": 3, "click": 497, "like": 4, "dislike": 1, "name": "케이피에프", "time": "2018-02-28 14:00"}, {"post_num": 0, "unique_id": 0, "click": 0, "like": 0, "dislike": 0, "name": "일정실업", "time": "2018-02-28 14:00"}, {"post_num": 12, "unique_id": 10, "click": 3683, "like": 11, "dislike": 19, "name": "현대제철", "time": "2018-02-28 14:00"}, {"post_num": 0, "unique_id": 0, "click": 0, "like": 0, "dislike": 0, "name": "일신방직", "time": "2018-02-28 14:00"}, {"post_num": 4, "unique_id": 4, "click": 179, "like": 1, "dislike": 6, "name": "이더블유케이", "time": "2018-02-28 14:00"}, {"post_num": 0, "unique_id": 0, "click": 0, "like": 0, "dislike": 0, "name": "경남스틸", "time": "2018-02-28 14:00"}, {"post_num": 0, "unique_id": 0, "click": 0, "like": 0, "dislike": 0, "name": "삼양통상", "time": "2018-02-28 14:00"}, {"post_num": 11, "unique_id": 11, "click": 3730, "like": 31, "dislike": 9, "name": "와이솔", "time": "2018-02-28 14:00"}, {"post_num": 2, "unique_id": 2, "click": 855, "like": 10, "dislike": 7, "name": "락앤락", "time": "2018-02-28 14:00"}, {"post_num": 24, "unique_id": 17, "click": 9971, "like": 55, "dislike": 81, "name": "제이콘텐트리", "time": "2018-02-28 14:00"}, {"post_num": 0, "unique_id": 0, "click": 0, "like": 0, "dislike": 0, "name": "WISCOM", "time": "2018-02-28 14:00"}, {"post_num": 2, "unique_id": 2, "click": 218, "like": 1, "dislike": 7, "name": "다우인큐브", "time": "2018-02-28 14:00"}, {"post_num": 2, "unique_id": 2, "click": 403, "like": 0, "dislike": 0, "name": "한온시스템", "time": "2018-02-28 14:00"}, {"post_num": 1, "unique_id": 1, "click": 76, "like": 0, "dislike": 0, "name": "코스메카코리아", "time": "2018-02-28 14:00"}, {"post_num": 28, "unique_id": 23, "click": 7546, "like": 46, "dislike": 33, "name": "케이사인", "time": "2018-02-28 14:00"}, {"post_num": 2, "unique_id": 2, "click": 237, "like": 2, "dislike": 7, "name": "삼기오토모티브", "time": "2018-02-28 14:00"}, {"post_num": 2, "unique_id": 1, "click": 317, "like": 3, "dislike": 2, "name": "넥스트칩", "time": "2018-02-28 14:00"}, {"post_num": 1, "unique_id": 1, "click": 100, "like": 1, "dislike": 2, "name": "엘엠에스", "time": "2018-02-28 14:00"}, {"post_num": 1, "unique_id": 1, "click": 13, "like": 0, "dislike": 0, "name": "인포바인", "time": "2018-02-28 14:00"}, {"post_num": 143, "unique_id": 75, "click": 37500, "like": 243, "dislike": 114, "name": "명문제약", "time": "2018-02-28 14:00"}, {"post_num": 4, "unique_id": 2, "click": 162, "like": 1, "dislike": 3, "name": "SBI핀테크솔루션즈", "time": "2018-02-28 14:00"}, {"post_num": 2, "unique_id": 2, "click": 228, "like": 0, "dislike": 0, "name": "크리스탈신소재", "time": "2018-02-28 14:00"}, {"post_num": 5, "unique_id": 2, "click": 1745, "like": 10, "dislike": 10, "name": "글로벌에스엠", "time": "2018-02-28 14:00"}, {"post_num": 13, "unique_id": 4, "click": 938, "like": 3, "dislike": 5, "name": "차이나그레이트", "time": "2018-02-28 14:00"}, {"post_num": 5, "unique_id": 5, "click": 582, "like": 6, "dislike": 0, "name": "시스웍", "time": "2018-02-28 14:00"}, {"post_num": 6, "unique_id": 5, "click": 298, "like": 1, "dislike": 1, "name": "지니언스", "time": "2018-02-28 14:00"}, {"post_num": 2, "unique_id": 2, "click": 192, "like": 0, "dislike": 1, "name": "샘표식품", "time": "2018-02-28 14:00"}, {"post_num": 16, "unique_id": 13, "click": 2088, "like": 14, "dislike": 14, "name": "신흥에스이씨", "time": "2018-02-28 14:00"}, {"post_num": 10, "unique_id": 8, "click": 2016, "like": 8, "dislike": 6, "name": "이오테크닉스", "time": "2018-02-28 14:00"}, {"post_num": 6, "unique_id": 6, "click": 2357, "like": 3, "dislike": 10, "name": "후성", "time": "2018-02-28 14:00"}, {"post_num": 0, "unique_id": 0, "click": 0, "like": 0, "dislike": 0, "name": "코텍", "time": "2018-02-28 14:00"}, {"post_num": 0, "unique_id": 0, "click": 0, "like": 0, "dislike": 0, "name": "삼성카드", "time": "2018-02-28 14:00"}, {"post_num": 1, "unique_id": 1, "click": 89, "like": 1, "dislike": 1, "name": "특수건설", "time": "2018-02-28 14:00"}, {"post_num": 0, "unique_id": 0, "click": 0, "like": 0, "dislike": 0, "name": "그랜드백화점", "time": "2018-02-28 14:00"}, {"post_num": 4, "unique_id": 4, "click": 1096, "like": 9, "dislike": 9, "name": "티에스인베스트먼트", "time": "2018-02-28 14:00"}, {"post_num": 0, "unique_id": 0, "click": 0, "like": 0, "dislike": 0, "name": "갤럭시아컴즈", "time": "2018-02-28 14:00"}, {"post_num": 1, "unique_id": 1, "click": 144, "like": 0, "dislike": 0, "name": "삼진엘앤디", "time": "2018-02-28 14:00"}, {"post_num": 6, "unique_id": 5, "click": 384, "like": 2, "dislike": 1, "name": "한전KPS", "time": "2018-02-28 14:00"}, {"post_num": 17, "unique_id": 10, "click": 3043, "like": 47, "dislike": 27, "name": "조아제약", "time": "2018-02-28 14:00"}, {"post_num": 2, "unique_id": 2, "click": 1015, "like": 1, "dislike": 6, "name": "대주전자재료", "time": "2018-02-28 14:00"}, {"post_num": 0, "unique_id": 0, "click": 0, "like": 0, "dislike": 0, "name": "디스플레이텍", "time": "2018-02-28 14:00"}, {"post_num": 1, "unique_id": 1, "click": 37, "like": 0, "dislike": 0, "name": "지어소프트", "time": "2018-02-28 14:00"}, {"post_num": 0, "unique_id": 0, "click": 0, "like": 0, "dislike": 0, "name": "아세아제지", "time": "2018-02-28 14:00"}, {"post_num": 1, "unique_id": 1, "click": 111, "like": 0, "dislike": 0, "name": "세아베스틸", "time": "2018-02-28 14:00"}, {"post_num": 6, "unique_id": 6, "click": 863, "like": 18, "dislike": 16, "name": "코라오홀딩스", "time": "2018-02-28 14:00"}, {"post_num": 3, "unique_id": 3, "click": 238, "like": 2, "dislike": 3, "name": "에스앤씨엔진그룹", "time": "2018-02-28 14:00"}, {"post_num": 0, "unique_id": 0, "click": 0, "like": 0, "dislike": 0, "name": "코스맥스비티아이", "time": "2018-02-28 14:00"}, {"post_num": 6, "unique_id": 5, "click": 1519, "like": 2, "dislike": 10, "name": "삼지전자", "time": "2018-02-28 14:00"}, {"post_num": 6, "unique_id": 5, "click": 851, "like": 14, "dislike": 2, "name": "강스템바이오텍", "time": "2018-02-28 14:00"}, {"post_num": 2, "unique_id": 1, "click": 280, "like": 0, "dislike": 1, "name": "애경유화", "time": "2018-02-28 14:00"}, {"post_num": 1, "unique_id": 1, "click": 100, "like": 0, "dislike": 0, "name": "한전산업", "time": "2018-02-28 14:00"}, {"post_num": 8, "unique_id": 7, "click": 2242, "like": 29, "dislike": 25, "name": "쎄트렉아이", "time": "2018-02-28 14:00"}, {"post_num": 36, "unique_id": 24, "click": 8423, "like": 48, "dislike": 27, "name": "파트론", "time": "2018-02-28 14:00"}, {"post_num": 0, "unique_id": 0, "click": 0, "like": 0, "dislike": 0, "name": "흥구석유", "time": "2018-02-28 14:00"}, {"post_num": 22, "unique_id": 16, "click": 6070, "like": 45, "dislike": 26, "name": "코오롱인더", "time": "2018-02-28 14:00"}, {"post_num": 16, "unique_id": 11, "click": 3497, "like": 26, "dislike": 21, "name": "지스마트글로벌", "time": "2018-02-28 14:00"}, {"post_num": 7, "unique_id": 7, "click": 2606, "like": 33, "dislike": 14, "name": "코미팜", "time": "2018-02-28 14:00"}, {"post_num": 4, "unique_id": 4, "click": 677, "like": 0, "dislike": 0, "name": "대창스틸", "time": "2018-02-28 14:00"}, {"post_num": 4, "unique_id": 4, "click": 718, "like": 2, "dislike": 1, "name": "골프존뉴딘", "time": "2018-02-28 14:00"}, {"post_num": 0, "unique_id": 0, "click": 0, "like": 0, "dislike": 0, "name": "테스", "time": "2018-02-28 14:00"}, {"post_num": 25, "unique_id": 20, "click": 7904, "like": 71, "dislike": 33, "name": "루트로닉", "time": "2018-02-28 14:00"}, {"post_num": 0, "unique_id": 0, "click": 0, "like": 0, "dislike": 0, "name": "이라이콤", "time": "2018-02-28 14:00"}, {"post_num": 2, "unique_id": 2, "click": 357, "like": 4, "dislike": 6, "name": "EG", "time": "2018-02-28 14:00"}, {"post_num": 9, "unique_id": 5, "click": 1927, "like": 11, "dislike": 8, "name": "신한지주", "time": "2018-02-28 14:00"}, {"post_num": 3, "unique_id": 3, "click": 884, "like": 3, "dislike": 7, "name": "대원미디어", "time": "2018-02-28 14:00"}, {"post_num": 79, "unique_id": 44, "click": 13289, "like": 310, "dislike": 66, "name": "BGF", "time": "2018-02-28 14:00"}]