[{"post_num": 2, "unique_id": 2, "click": 304, "like": 5, "dislike": 0, "name": "오스템임플란트", "time": "2018-02-22 13:50"}, {"post_num": 54, "unique_id": 32, "click": 22706, "like": 158, "dislike": 87, "name": "두산인프라코어", "time": "2018-02-22 13:50"}, {"post_num": 18, "unique_id": 13, "click": 5859, "like": 20, "dislike": 28, "name": "유니셈", "time": "2018-02-22 13:50"}, {"post_num": 68, "unique_id": 43, "click": 16142, "like": 171, "dislike": 95, "name": "BGF", "time": "2018-02-22 13:50"}, {"post_num": 26, "unique_id": 18, "click": 8692, "like": 48, "dislike": 46, "name": "한화테크윈", "time": "2018-02-22 13:50"}, {"post_num": 36, "unique_id": 29, "click": 6818, "like": 32, "dislike": 9, "name": "비상교육", "time": "2018-02-22 13:50"}, {"post_num": 8, "unique_id": 8, "click": 3631, "like": 17, "dislike": 17, "name": "LG이노텍", "time": "2018-02-22 13:50"}, {"post_num": 29, "unique_id": 16, "click": 12604, "like": 46, "dislike": 49, "name": "파라다이스", "time": "2018-02-22 13:50"}, {"post_num": 35, "unique_id": 20, "click": 9916, "like": 41, "dislike": 49, "name": "다날", "time": "2018-02-22 13:50"}, {"post_num": 6, "unique_id": 5, "click": 2114, "like": 17, "dislike": 12, "name": "폭스브레인", "time": "2018-02-22 13:50"}, {"post_num": 10, "unique_id": 4, "click": 1316, "like": 7, "dislike": 1, "name": "이에스브이", "time": "2018-02-22 13:50"}, {"post_num": 47, "unique_id": 32, "click": 17474, "like": 130, "dislike": 71, "name": "에이프로젠KIC", "time": "2018-02-22 13:50"}, {"post_num": 12, "unique_id": 10, "click": 5443, "like": 43, "dislike": 11, "name": "디에스티로봇", "time": "2018-02-22 13:50"}, {"post_num": 4, "unique_id": 4, "click": 1713, "like": 6, "dislike": 3, "name": "에코프로", "time": "2018-02-22 13:50"}, {"post_num": 28, "unique_id": 17, "click": 5801, "like": 29, "dislike": 18, "name": "LIG넥스원", "time": "2018-02-22 13:50"}, {"post_num": 12, "unique_id": 11, "click": 5799, "like": 51, "dislike": 23, "name": "쇼박스", "time": "2018-02-22 13:50"}, {"post_num": 15, "unique_id": 9, "click": 6113, "like": 29, "dislike": 29, "name": "삼성에스디에스", "time": "2018-02-22 13:50"}, {"post_num": 17, "unique_id": 10, "click": 3545, "like": 20, "dislike": 18, "name": "대한항공", "time": "2018-02-22 13:50"}, {"post_num": 5, "unique_id": 4, "click": 892, "like": 13, "dislike": 7, "name": "제일홀딩스", "time": "2018-02-22 13:50"}, {"post_num": 6, "unique_id": 6, "click": 2072, "like": 18, "dislike": 24, "name": "우리로", "time": "2018-02-22 13:50"}, {"post_num": 2, "unique_id": 2, "click": 191, "like": 1, "dislike": 1, "name": "SK", "time": "2018-02-22 13:50"}, {"post_num": 1, "unique_id": 1, "click": 135, "like": 2, "dislike": 1, "name": "NH투자증권", "time": "2018-02-22 13:50"}, {"post_num": 4, "unique_id": 4, "click": 2561, "like": 22, "dislike": 13, "name": "마크로젠", "time": "2018-02-22 13:50"}, {"post_num": 31, "unique_id": 25, "click": 8728, "like": 114, "dislike": 80, "name": "내츄럴엔도텍", "time": "2018-02-22 13:50"}, {"post_num": 205, "unique_id": 79, "click": 38303, "like": 348, "dislike": 242, "name": "완리", "time": "2018-02-22 13:50"}, {"post_num": 24, "unique_id": 20, "click": 6684, "like": 110, "dislike": 70, "name": "대우건설", "time": "2018-02-22 13:50"}, {"post_num": 0, "unique_id": 0, "click": 0, "like": 0, "dislike": 0, "name": "아이씨케이", "time": "2018-02-22 13:50"}, {"post_num": 5, "unique_id": 5, "click": 597, "like": 2, "dislike": 3, "name": "인터파크홀딩스", "time": "2018-02-22 13:50"}, {"post_num": 2, "unique_id": 2, "click": 916, "like": 13, "dislike": 3, "name": "씨젠", "time": "2018-02-22 13:50"}, {"post_num": 17, "unique_id": 14, "click": 3175, "like": 8, "dislike": 7, "name": "이원컴포텍", "time": "2018-02-22 13:50"}, {"post_num": 5, "unique_id": 5, "click": 1246, "like": 13, "dislike": 4, "name": "현대제철", "time": "2018-02-22 13:50"}, {"post_num": 0, "unique_id": 0, "click": 0, "like": 0, "dislike": 0, "name": "일신방직", "time": "2018-02-22 13:50"}, {"post_num": 0, "unique_id": 0, "click": 0, "like": 0, "dislike": 0, "name": "인팩", "time": "2018-02-22 13:50"}, {"post_num": 0, "unique_id": 0, "click": 0, "like": 0, "dislike": 0, "name": "원림", "time": "2018-02-22 13:50"}, {"post_num": 2, "unique_id": 2, "click": 941, "like": 7, "dislike": 6, "name": "현대로보틱스", "time": "2018-02-22 13:50"}, {"post_num": 17, "unique_id": 15, "click": 4735, "like": 32, "dislike": 43, "name": "SK케미칼", "time": "2018-02-22 13:50"}, {"post_num": 21, "unique_id": 3, "click": 1341, "like": 2, "dislike": 1, "name": "해마로푸드서비스", "time": "2018-02-22 13:50"}, {"post_num": 0, "unique_id": 0, "click": 0, "like": 0, "dislike": 0, "name": "메가스터디교육", "time": "2018-02-22 13:50"}, {"post_num": 4, "unique_id": 4, "click": 1611, "like": 3, "dislike": 12, "name": "포스코 ICT", "time": "2018-02-22 13:50"}, {"post_num": 5, "unique_id": 5, "click": 1696, "like": 7, "dislike": 9, "name": "롯데케미칼", "time": "2018-02-22 13:50"}, {"post_num": 3, "unique_id": 3, "click": 382, "like": 1, "dislike": 3, "name": "메리츠종금증권", "time": "2018-02-22 13:50"}, {"post_num": 1, "unique_id": 1, "click": 71, "like": 0, "dislike": 0, "name": "서연이화", "time": "2018-02-22 13:50"}, {"post_num": 87, "unique_id": 36, "click": 12982, "like": 107, "dislike": 62, "name": "골든센츄리", "time": "2018-02-22 13:50"}, {"post_num": 1, "unique_id": 1, "click": 168, "like": 2, "dislike": 2, "name": "GST", "time": "2018-02-22 13:50"}, {"post_num": 4, "unique_id": 4, "click": 184, "like": 3, "dislike": 1, "name": "모아텍", "time": "2018-02-22 13:50"}, {"post_num": 1, "unique_id": 1, "click": 35, "like": 1, "dislike": 0, "name": "대원산업", "time": "2018-02-22 13:50"}, {"post_num": 10, "unique_id": 9, "click": 2633, "like": 40, "dislike": 12, "name": "앱클론", "time": "2018-02-22 13:50"}, {"post_num": 5, "unique_id": 5, "click": 877, "like": 29, "dislike": 13, "name": "동아엘텍", "time": "2018-02-22 13:50"}, {"post_num": 5, "unique_id": 3, "click": 1009, "like": 4, "dislike": 6, "name": "유니테스트", "time": "2018-02-22 13:50"}, {"post_num": 6, "unique_id": 2, "click": 612, "like": 4, "dislike": 9, "name": "이노와이어리스", "time": "2018-02-22 13:50"}, {"post_num": 0, "unique_id": 0, "click": 0, "like": 0, "dislike": 0, "name": "태양", "time": "2018-02-22 13:50"}, {"post_num": 2, "unique_id": 2, "click": 433, "like": 1, "dislike": 0, "name": "코웨이", "time": "2018-02-22 13:50"}, {"post_num": 4, "unique_id": 4, "click": 1002, "like": 15, "dislike": 12, "name": "잇츠한불", "time": "2018-02-22 13:50"}, {"post_num": 37, "unique_id": 25, "click": 12046, "like": 108, "dislike": 62, "name": "액션스퀘어", "time": "2018-02-22 13:50"}, {"post_num": 7, "unique_id": 6, "click": 1063, "like": 18, "dislike": 7, "name": "현성바이탈", "time": "2018-02-22 13:50"}, {"post_num": 1, "unique_id": 1, "click": 129, "like": 3, "dislike": 0, "name": "휴메딕스", "time": "2018-02-22 13:50"}, {"post_num": 7, "unique_id": 5, "click": 1791, "like": 25, "dislike": 16, "name": "락앤락", "time": "2018-02-22 13:50"}, {"post_num": 0, "unique_id": 0, "click": 0, "like": 0, "dislike": 0, "name": "인화정공", "time": "2018-02-22 13:50"}, {"post_num": 11, "unique_id": 8, "click": 5122, "like": 44, "dislike": 27, "name": "루트로닉", "time": "2018-02-22 13:50"}, {"post_num": 2, "unique_id": 2, "click": 234, "like": 2, "dislike": 0, "name": "알테오젠", "time": "2018-02-22 13:50"}, {"post_num": 3, "unique_id": 3, "click": 282, "like": 4, "dislike": 2, "name": "풍산", "time": "2018-02-22 13:50"}, {"post_num": 43, "unique_id": 24, "click": 5548, "like": 94, "dislike": 59, "name": "빅텍", "time": "2018-02-22 13:50"}, {"post_num": 8, "unique_id": 7, "click": 1010, "like": 20, "dislike": 6, "name": "에스아이리소스", "time": "2018-02-22 13:50"}, {"post_num": 53, "unique_id": 25, "click": 10439, "like": 137, "dislike": 113, "name": "KD건설", "time": "2018-02-22 13:50"}, {"post_num": 0, "unique_id": 0, "click": 0, "like": 0, "dislike": 0, "name": "동서", "time": "2018-02-22 13:50"}, {"post_num": 0, "unique_id": 0, "click": 0, "like": 0, "dislike": 0, "name": "현대차투자증권", "time": "2018-02-22 13:50"}, {"post_num": 4, "unique_id": 4, "click": 814, "like": 10, "dislike": 3, "name": "코오롱인더", "time": "2018-02-22 13:50"}, {"post_num": 11, "unique_id": 11, "click": 3334, "like": 54, "dislike": 26, "name": "지스마트글로벌", "time": "2018-02-22 13:50"}, {"post_num": 29, "unique_id": 21, "click": 14628, "like": 27, "dislike": 30, "name": "실리콘웍스", "time": "2018-02-22 13:50"}, {"post_num": 6, "unique_id": 5, "click": 2312, "like": 13, "dislike": 17, "name": "두산엔진", "time": "2018-02-22 13:50"}, {"post_num": 2, "unique_id": 1, "click": 191, "like": 2, "dislike": 0, "name": "디스플레이텍", "time": "2018-02-22 13:50"}, {"post_num": 6, "unique_id": 2, "click": 1036, "like": 2, "dislike": 10, "name": "우리조명", "time": "2018-02-22 13:50"}, {"post_num": 2, "unique_id": 2, "click": 845, "like": 3, "dislike": 3, "name": "삼성생명", "time": "2018-02-22 13:50"}, {"post_num": 8, "unique_id": 6, "click": 2452, "like": 10, "dislike": 5, "name": "지엠비코리아", "time": "2018-02-22 13:50"}, {"post_num": 4, "unique_id": 4, "click": 327, "like": 5, "dislike": 0, "name": "한국내화", "time": "2018-02-22 13:50"}, {"post_num": 12, "unique_id": 10, "click": 4110, "like": 29, "dislike": 37, "name": "제이콘텐트리", "time": "2018-02-22 13:50"}, {"post_num": 2, "unique_id": 2, "click": 193, "like": 3, "dislike": 3, "name": "한국전자홀딩스", "time": "2018-02-22 13:50"}, {"post_num": 22, "unique_id": 13, "click": 4938, "like": 23, "dislike": 13, "name": "일동제약", "time": "2018-02-22 13:50"}, {"post_num": 16, "unique_id": 13, "click": 2147, "like": 24, "dislike": 22, "name": "삼기오토모티브", "time": "2018-02-22 13:50"}, {"post_num": 40, "unique_id": 27, "click": 8187, "like": 107, "dislike": 91, "name": "씨그널엔터테인먼트그룹", "time": "2018-02-22 13:50"}, {"post_num": 1, "unique_id": 1, "click": 326, "like": 7, "dislike": 1, "name": "메디프론", "time": "2018-02-22 13:50"}, {"post_num": 2, "unique_id": 2, "click": 332, "like": 0, "dislike": 2, "name": "NHN한국사이버결제", "time": "2018-02-22 13:50"}, {"post_num": 2, "unique_id": 2, "click": 34, "like": 4, "dislike": 0, "name": "NE능률", "time": "2018-02-22 13:50"}, {"post_num": 3, "unique_id": 3, "click": 303, "like": 3, "dislike": 0, "name": "해덕파워웨이", "time": "2018-02-22 13:50"}, {"post_num": 8, "unique_id": 7, "click": 2710, "like": 14, "dislike": 8, "name": "이트론", "time": "2018-02-22 13:50"}, {"post_num": 42, "unique_id": 24, "click": 14441, "like": 113, "dislike": 65, "name": "소리바다", "time": "2018-02-22 13:50"}, {"post_num": 4, "unique_id": 3, "click": 1087, "like": 7, "dislike": 1, "name": "에스엠", "time": "2018-02-22 13:50"}, {"post_num": 0, "unique_id": 0, "click": 0, "like": 0, "dislike": 0, "name": "이건홀딩스", "time": "2018-02-22 13:50"}, {"post_num": 0, "unique_id": 0, "click": 0, "like": 0, "dislike": 0, "name": "틸론", "time": "2018-02-22 13:50"}, {"post_num": 23, "unique_id": 14, "click": 5945, "like": 33, "dislike": 29, "name": "프로스테믹스", "time": "2018-02-22 13:50"}, {"post_num": 0, "unique_id": 0, "click": 0, "like": 0, "dislike": 0, "name": "연이정보통신", "time": "2018-02-22 13:50"}, {"post_num": 14, "unique_id": 12, "click": 4278, "like": 20, "dislike": 29, "name": "엠케이전자", "time": "2018-02-22 13:50"}, {"post_num": 7, "unique_id": 6, "click": 1928, "like": 26, "dislike": 17, "name": "씨에스윈드", "time": "2018-02-22 13:50"}, {"post_num": 0, "unique_id": 0, "click": 0, "like": 0, "dislike": 0, "name": "SIMPAC Metal", "time": "2018-02-22 13:50"}, {"post_num": 19, "unique_id": 11, "click": 3295, "like": 19, "dislike": 12, "name": "대창스틸", "time": "2018-02-22 13:50"}, {"post_num": 0, "unique_id": 0, "click": 0, "like": 0, "dislike": 0, "name": "이크레더블", "time": "2018-02-22 13:50"}, {"post_num": 0, "unique_id": 0, "click": 0, "like": 0, "dislike": 0, "name": "에스텍", "time": "2018-02-22 13:50"}, {"post_num": 18, "unique_id": 12, "click": 2841, "like": 23, "dislike": 26, "name": "화일약품", "time": "2018-02-22 13:50"}, {"post_num": 0, "unique_id": 0, "click": 0, "like": 0, "dislike": 0, "name": "경남스틸", "time": "2018-02-22 13:50"}, {"post_num": 1, "unique_id": 1, "click": 48, "like": 0, "dislike": 1, "name": "혜인", "time": "2018-02-22 13:50"}, {"post_num": 4, "unique_id": 3, "click": 766, "like": 3, "dislike": 4, "name": "한국화장품", "time": "2018-02-22 13:50"}, {"post_num": 6, "unique_id": 5, "click": 1620, "like": 19, "dislike": 8, "name": "코오롱생명과학", "time": "2018-02-22 13:50"}, {"post_num": 1, "unique_id": 1, "click": 46, "like": 0, "dislike": 0, "name": "가비아", "time": "2018-02-22 13:50"}, {"post_num": 0, "unique_id": 0, "click": 0, "like": 0, "dislike": 0, "name": "새론오토모티브", "time": "2018-02-22 13:50"}, {"post_num": 0, "unique_id": 0, "click": 0, "like": 0, "dislike": 0, "name": "지역난방공사", "time": "2018-02-22 13:50"}, {"post_num": 31, "unique_id": 24, "click": 14427, "like": 117, "dislike": 47, "name": "에이프로젠제약", "time": "2018-02-22 13:50"}, {"post_num": 16, "unique_id": 8, "click": 2512, "like": 29, "dislike": 38, "name": "켐트로스", "time": "2018-02-22 13:50"}, {"post_num": 3, "unique_id": 3, "click": 555, "like": 1, "dislike": 2, "name": "인터로조", "time": "2018-02-22 13:50"}, {"post_num": 1, "unique_id": 1, "click": 381, "like": 4, "dislike": 8, "name": "LG하우시스", "time": "2018-02-22 13:50"}, {"post_num": 3, "unique_id": 3, "click": 62, "like": 0, "dislike": 0, "name": "캐스텍코리아", "time": "2018-02-22 13:50"}, {"post_num": 26, "unique_id": 18, "click": 10383, "like": 76, "dislike": 54, "name": "홈캐스트", "time": "2018-02-22 13:50"}, {"post_num": 27, "unique_id": 17, "click": 5657, "like": 65, "dislike": 46, "name": "옴니텔", "time": "2018-02-22 13:50"}, {"post_num": 2, "unique_id": 2, "click": 715, "like": 1, "dislike": 10, "name": "디피씨", "time": "2018-02-22 13:50"}, {"post_num": 0, "unique_id": 0, "click": 0, "like": 0, "dislike": 0, "name": "방림", "time": "2018-02-22 13:50"}, {"post_num": 1, "unique_id": 1, "click": 8, "like": 0, "dislike": 0, "name": "켐트로닉스", "time": "2018-02-22 13:50"}, {"post_num": 0, "unique_id": 0, "click": 0, "like": 0, "dislike": 0, "name": "SIMPAC", "time": "2018-02-22 13:50"}, {"post_num": 4, "unique_id": 4, "click": 1353, "like": 14, "dislike": 3, "name": "한진칼", "time": "2018-02-22 13:50"}, {"post_num": 11, "unique_id": 7, "click": 3795, "like": 32, "dislike": 15, "name": "메디포스트", "time": "2018-02-22 13:50"}, {"post_num": 2, "unique_id": 2, "click": 209, "like": 1, "dislike": 3, "name": "우리손에프앤지", "time": "2018-02-22 13:50"}, {"post_num": 1, "unique_id": 1, "click": 109, "like": 0, "dislike": 0, "name": "애경유화", "time": "2018-02-22 13:50"}, {"post_num": 7, "unique_id": 7, "click": 2155, "like": 14, "dislike": 3, "name": "옵트론텍", "time": "2018-02-22 13:50"}, {"post_num": 2, "unique_id": 2, "click": 202, "like": 0, "dislike": 0, "name": "한국금융지주", "time": "2018-02-22 13:50"}]