[{"post_num": 22, "unique_id": 20, "click": 8782, "like": 53, "dislike": 19, "name": "SKC코오롱PI", "time": "2018-02-23 12:20"}, {"post_num": 38, "unique_id": 25, "click": 9001, "like": 130, "dislike": 54, "name": "홈캐스트", "time": "2018-02-23 12:20"}, {"post_num": 74, "unique_id": 47, "click": 17883, "like": 52, "dislike": 40, "name": "고려제약", "time": "2018-02-23 12:20"}, {"post_num": 47, "unique_id": 27, "click": 7334, "like": 110, "dislike": 112, "name": "미투온", "time": "2018-02-23 12:20"}, {"post_num": 34, "unique_id": 20, "click": 8465, "like": 70, "dislike": 32, "name": "한화테크윈", "time": "2018-02-23 12:20"}, {"post_num": 13, "unique_id": 12, "click": 6887, "like": 77, "dislike": 28, "name": "EMW", "time": "2018-02-23 12:20"}, {"post_num": 18, "unique_id": 16, "click": 8525, "like": 94, "dislike": 25, "name": "삼성물산", "time": "2018-02-23 12:20"}, {"post_num": 21, "unique_id": 17, "click": 9727, "like": 49, "dislike": 12, "name": "코스모화학", "time": "2018-02-23 12:20"}, {"post_num": 2, "unique_id": 2, "click": 290, "like": 2, "dislike": 2, "name": "레고켐바이오", "time": "2018-02-23 12:20"}, {"post_num": 3, "unique_id": 2, "click": 896, "like": 5, "dislike": 10, "name": "KG이니시스", "time": "2018-02-23 12:20"}, {"post_num": 29, "unique_id": 23, "click": 8972, "like": 197, "dislike": 53, "name": "JYP Ent.", "time": "2018-02-23 12:20"}, {"post_num": 2, "unique_id": 2, "click": 519, "like": 8, "dislike": 5, "name": "씨에스윈드", "time": "2018-02-23 12:20"}, {"post_num": 1, "unique_id": 1, "click": 189, "like": 2, "dislike": 1, "name": "KG모빌리언스", "time": "2018-02-23 12:20"}, {"post_num": 6, "unique_id": 4, "click": 1007, "like": 7, "dislike": 2, "name": "삼성생명", "time": "2018-02-23 12:20"}, {"post_num": 40, "unique_id": 26, "click": 11129, "like": 95, "dislike": 51, "name": "셀루메드", "time": "2018-02-23 12:20"}, {"post_num": 22, "unique_id": 11, "click": 3743, "like": 19, "dislike": 10, "name": "대한항공", "time": "2018-02-23 12:20"}, {"post_num": 16, "unique_id": 11, "click": 4582, "like": 30, "dislike": 37, "name": "롯데지주", "time": "2018-02-23 12:20"}, {"post_num": 37, "unique_id": 28, "click": 17262, "like": 53, "dislike": 23, "name": "AP시스템", "time": "2018-02-23 12:20"}, {"post_num": 5, "unique_id": 5, "click": 795, "like": 4, "dislike": 4, "name": "휘닉스소재", "time": "2018-02-23 12:20"}, {"post_num": 138, "unique_id": 61, "click": 30282, "like": 121, "dislike": 194, "name": "SBI인베스트먼트", "time": "2018-02-23 12:20"}, {"post_num": 5, "unique_id": 5, "click": 1247, "like": 10, "dislike": 11, "name": "메디톡스", "time": "2018-02-23 12:20"}, {"post_num": 15, "unique_id": 11, "click": 3250, "like": 14, "dislike": 8, "name": "씨트리", "time": "2018-02-23 12:20"}, {"post_num": 0, "unique_id": 0, "click": 0, "like": 0, "dislike": 0, "name": "이크레더블", "time": "2018-02-23 12:20"}, {"post_num": 5, "unique_id": 5, "click": 1051, "like": 4, "dislike": 2, "name": "현대제철", "time": "2018-02-23 12:20"}, {"post_num": 55, "unique_id": 41, "click": 23426, "like": 147, "dislike": 46, "name": "비에이치", "time": "2018-02-23 12:20"}, {"post_num": 5, "unique_id": 5, "click": 967, "like": 5, "dislike": 4, "name": "옵트론텍", "time": "2018-02-23 12:20"}, {"post_num": 3, "unique_id": 3, "click": 380, "like": 6, "dislike": 2, "name": "하림홀딩스", "time": "2018-02-23 12:20"}, {"post_num": 34, "unique_id": 24, "click": 5230, "like": 64, "dislike": 22, "name": "골든센츄리", "time": "2018-02-23 12:20"}, {"post_num": 2, "unique_id": 2, "click": 502, "like": 11, "dislike": 1, "name": "와이엠티", "time": "2018-02-23 12:20"}, {"post_num": 0, "unique_id": 0, "click": 0, "like": 0, "dislike": 0, "name": "아주캐피탈", "time": "2018-02-23 12:20"}, {"post_num": 4, "unique_id": 4, "click": 710, "like": 7, "dislike": 7, "name": "현대건설", "time": "2018-02-23 12:20"}, {"post_num": 2, "unique_id": 2, "click": 116, "like": 1, "dislike": 0, "name": "코스메카코리아", "time": "2018-02-23 12:20"}, {"post_num": 2, "unique_id": 2, "click": 81, "like": 0, "dislike": 0, "name": "흥국에프엔비", "time": "2018-02-23 12:20"}, {"post_num": 4, "unique_id": 2, "click": 228, "like": 1, "dislike": 0, "name": "솔브레인", "time": "2018-02-23 12:20"}, {"post_num": 66, "unique_id": 51, "click": 12161, "like": 71, "dislike": 31, "name": "이디", "time": "2018-02-23 12:20"}, {"post_num": 0, "unique_id": 0, "click": 0, "like": 0, "dislike": 0, "name": "화천기계", "time": "2018-02-23 12:20"}, {"post_num": 11, "unique_id": 8, "click": 1302, "like": 2, "dislike": 0, "name": "알테오젠", "time": "2018-02-23 12:20"}, {"post_num": 2, "unique_id": 2, "click": 199, "like": 4, "dislike": 1, "name": "쿠쿠홀딩스", "time": "2018-02-23 12:20"}, {"post_num": 5, "unique_id": 5, "click": 568, "like": 8, "dislike": 4, "name": "화진", "time": "2018-02-23 12:20"}, {"post_num": 2, "unique_id": 2, "click": 217, "like": 0, "dislike": 0, "name": "대신증권", "time": "2018-02-23 12:20"}, {"post_num": 6, "unique_id": 2, "click": 416, "like": 0, "dislike": 0, "name": "차이나그레이트", "time": "2018-02-23 12:20"}, {"post_num": 59, "unique_id": 38, "click": 12920, "like": 95, "dislike": 44, "name": "시큐브", "time": "2018-02-23 12:20"}, {"post_num": 7, "unique_id": 7, "click": 2146, "like": 14, "dislike": 7, "name": "에코프로", "time": "2018-02-23 12:20"}, {"post_num": 3, "unique_id": 3, "click": 1005, "like": 6, "dislike": 15, "name": "씨씨에스", "time": "2018-02-23 12:20"}, {"post_num": 4, "unique_id": 3, "click": 528, "like": 0, "dislike": 0, "name": "감마누", "time": "2018-02-23 12:20"}, {"post_num": 8, "unique_id": 7, "click": 1859, "like": 20, "dislike": 5, "name": "코오롱생명과학", "time": "2018-02-23 12:20"}, {"post_num": 33, "unique_id": 17, "click": 5962, "like": 41, "dislike": 48, "name": "엘컴텍", "time": "2018-02-23 12:20"}, {"post_num": 0, "unique_id": 0, "click": 0, "like": 0, "dislike": 0, "name": "아세아제지", "time": "2018-02-23 12:20"}, {"post_num": 16, "unique_id": 13, "click": 2770, "like": 57, "dislike": 11, "name": "드림시큐리티", "time": "2018-02-23 12:20"}, {"post_num": 0, "unique_id": 0, "click": 0, "like": 0, "dislike": 0, "name": "고영", "time": "2018-02-23 12:20"}, {"post_num": 5, "unique_id": 3, "click": 655, "like": 3, "dislike": 6, "name": "이엠텍", "time": "2018-02-23 12:20"}, {"post_num": 0, "unique_id": 0, "click": 0, "like": 0, "dislike": 0, "name": "SIMPAC Metal", "time": "2018-02-23 12:20"}, {"post_num": 0, "unique_id": 0, "click": 0, "like": 0, "dislike": 0, "name": "펩트론", "time": "2018-02-23 12:20"}, {"post_num": 0, "unique_id": 0, "click": 0, "like": 0, "dislike": 0, "name": "인터로조", "time": "2018-02-23 12:20"}, {"post_num": 0, "unique_id": 0, "click": 0, "like": 0, "dislike": 0, "name": "디지아이", "time": "2018-02-23 12:20"}, {"post_num": 3, "unique_id": 3, "click": 582, "like": 0, "dislike": 0, "name": "원익", "time": "2018-02-23 12:20"}, {"post_num": 1, "unique_id": 1, "click": 86, "like": 0, "dislike": 1, "name": "세아베스틸", "time": "2018-02-23 12:20"}, {"post_num": 5, "unique_id": 5, "click": 1126, "like": 12, "dislike": 7, "name": "코오롱인더", "time": "2018-02-23 12:20"}, {"post_num": 7, "unique_id": 6, "click": 2503, "like": 32, "dislike": 29, "name": "대화제약", "time": "2018-02-23 12:20"}, {"post_num": 2, "unique_id": 2, "click": 523, "like": 1, "dislike": 2, "name": "경남제약", "time": "2018-02-23 12:20"}, {"post_num": 3, "unique_id": 2, "click": 881, "like": 9, "dislike": 10, "name": "라온시큐어", "time": "2018-02-23 12:20"}, {"post_num": 2, "unique_id": 2, "click": 45, "like": 3, "dislike": 0, "name": "NICE", "time": "2018-02-23 12:20"}, {"post_num": 0, "unique_id": 0, "click": 0, "like": 0, "dislike": 0, "name": "동방", "time": "2018-02-23 12:20"}, {"post_num": 5, "unique_id": 5, "click": 414, "like": 4, "dislike": 3, "name": "SG", "time": "2018-02-23 12:20"}, {"post_num": 4, "unique_id": 4, "click": 225, "like": 0, "dislike": 3, "name": "미스터블루", "time": "2018-02-23 12:20"}, {"post_num": 26, "unique_id": 20, "click": 7945, "like": 60, "dislike": 18, "name": "사파이어테크놀로지", "time": "2018-02-23 12:20"}, {"post_num": 1, "unique_id": 1, "click": 77, "like": 1, "dislike": 1, "name": "조선선재", "time": "2018-02-23 12:20"}, {"post_num": 2, "unique_id": 2, "click": 28, "like": 0, "dislike": 1, "name": "한창산업", "time": "2018-02-23 12:20"}, {"post_num": 19, "unique_id": 11, "click": 3024, "like": 11, "dislike": 14, "name": "대봉엘에스", "time": "2018-02-23 12:20"}, {"post_num": 20, "unique_id": 10, "click": 4361, "like": 61, "dislike": 58, "name": "대웅제약", "time": "2018-02-23 12:20"}, {"post_num": 3, "unique_id": 3, "click": 837, "like": 12, "dislike": 0, "name": "키이스트", "time": "2018-02-23 12:20"}, {"post_num": 0, "unique_id": 0, "click": 0, "like": 0, "dislike": 0, "name": "에코플라스틱", "time": "2018-02-23 12:20"}, {"post_num": 7, "unique_id": 7, "click": 1628, "like": 22, "dislike": 8, "name": "성도이엔지", "time": "2018-02-23 12:20"}, {"post_num": 4, "unique_id": 4, "click": 454, "like": 0, "dislike": 0, "name": "삼일", "time": "2018-02-23 12:20"}, {"post_num": 1, "unique_id": 1, "click": 52, "like": 0, "dislike": 0, "name": "대진디엠피", "time": "2018-02-23 12:20"}, {"post_num": 0, "unique_id": 0, "click": 0, "like": 0, "dislike": 0, "name": "웰크론한텍", "time": "2018-02-23 12:20"}, {"post_num": 0, "unique_id": 0, "click": 0, "like": 0, "dislike": 0, "name": "CJ오쇼핑", "time": "2018-02-23 12:20"}, {"post_num": 1, "unique_id": 1, "click": 93, "like": 1, "dislike": 0, "name": "더존비즈온", "time": "2018-02-23 12:20"}, {"post_num": 0, "unique_id": 0, "click": 0, "like": 0, "dislike": 0, "name": "인화정공", "time": "2018-02-23 12:20"}, {"post_num": 3, "unique_id": 3, "click": 838, "like": 2, "dislike": 14, "name": "맥쿼리인프라", "time": "2018-02-23 12:20"}, {"post_num": 2, "unique_id": 2, "click": 116, "like": 1, "dislike": 1, "name": "이상네트웍스", "time": "2018-02-23 12:20"}, {"post_num": 0, "unique_id": 0, "click": 0, "like": 0, "dislike": 0, "name": "엘엠에스", "time": "2018-02-23 12:20"}, {"post_num": 1, "unique_id": 1, "click": 9, "like": 0, "dislike": 0, "name": "멕아이씨에스", "time": "2018-02-23 12:20"}, {"post_num": 0, "unique_id": 0, "click": 0, "like": 0, "dislike": 0, "name": "하이록코리아", "time": "2018-02-23 12:20"}, {"post_num": 0, "unique_id": 0, "click": 0, "like": 0, "dislike": 0, "name": "이씨에스", "time": "2018-02-23 12:20"}, {"post_num": 0, "unique_id": 0, "click": 0, "like": 0, "dislike": 0, "name": "화성밸브", "time": "2018-02-23 12:20"}, {"post_num": 2, "unique_id": 2, "click": 259, "like": 0, "dislike": 2, "name": "애경유화", "time": "2018-02-23 12:20"}, {"post_num": 6, "unique_id": 4, "click": 1459, "like": 11, "dislike": 22, "name": "안트로젠", "time": "2018-02-23 12:20"}, {"post_num": 7, "unique_id": 7, "click": 2925, "like": 11, "dislike": 2, "name": "에이디칩스", "time": "2018-02-23 12:20"}, {"post_num": 9, "unique_id": 6, "click": 855, "like": 13, "dislike": 2, "name": "삼영엠텍", "time": "2018-02-23 12:20"}, {"post_num": 21, "unique_id": 15, "click": 6087, "like": 58, "dislike": 51, "name": "대우건설", "time": "2018-02-23 12:20"}, {"post_num": 0, "unique_id": 0, "click": 0, "like": 0, "dislike": 0, "name": "세아특수강", "time": "2018-02-23 12:20"}, {"post_num": 3, "unique_id": 3, "click": 812, "like": 8, "dislike": 5, "name": "CJ", "time": "2018-02-23 12:20"}, {"post_num": 4, "unique_id": 4, "click": 245, "like": 2, "dislike": 2, "name": "엔에스", "time": "2018-02-23 12:20"}, {"post_num": 0, "unique_id": 0, "click": 0, "like": 0, "dislike": 0, "name": "네오오토", "time": "2018-02-23 12:20"}, {"post_num": 3, "unique_id": 2, "click": 535, "like": 5, "dislike": 3, "name": "아비스타", "time": "2018-02-23 12:20"}, {"post_num": 0, "unique_id": 0, "click": 0, "like": 0, "dislike": 0, "name": "캐스텍코리아", "time": "2018-02-23 12:20"}, {"post_num": 40, "unique_id": 20, "click": 19987, "like": 246, "dislike": 162, "name": "에이치엘비생명과학", "time": "2018-02-23 12:20"}, {"post_num": 0, "unique_id": 0, "click": 0, "like": 0, "dislike": 0, "name": "S&T모티브", "time": "2018-02-23 12:20"}]