[{"post_num": 7, "unique_id": 7, "click": 2167, "like": 17, "dislike": 7, "name": "루트로닉", "time": "2018-02-26 11:40"}, {"post_num": 26, "unique_id": 12, "click": 10721, "like": 60, "dislike": 52, "name": "텍셀네트컴", "time": "2018-02-26 11:40"}, {"post_num": 3, "unique_id": 3, "click": 745, "like": 4, "dislike": 4, "name": "환인제약", "time": "2018-02-26 11:40"}, {"post_num": 5, "unique_id": 5, "click": 1126, "like": 23, "dislike": 9, "name": "와이엠티", "time": "2018-02-26 11:40"}, {"post_num": 1, "unique_id": 1, "click": 255, "like": 9, "dislike": 3, "name": "한진칼", "time": "2018-02-26 11:40"}, {"post_num": 2, "unique_id": 2, "click": 229, "like": 0, "dislike": 2, "name": "씨젠", "time": "2018-02-26 11:40"}, {"post_num": 3, "unique_id": 3, "click": 645, "like": 4, "dislike": 2, "name": "넵튠", "time": "2018-02-26 11:40"}, {"post_num": 0, "unique_id": 0, "click": 0, "like": 0, "dislike": 0, "name": "진양홀딩스", "time": "2018-02-26 11:40"}, {"post_num": 15, "unique_id": 12, "click": 5973, "like": 47, "dislike": 20, "name": "주성엔지니어링", "time": "2018-02-26 11:40"}, {"post_num": 0, "unique_id": 0, "click": 0, "like": 0, "dislike": 0, "name": "만도", "time": "2018-02-26 11:40"}, {"post_num": 13, "unique_id": 7, "click": 2921, "like": 63, "dislike": 43, "name": "대웅제약", "time": "2018-02-26 11:40"}, {"post_num": 18, "unique_id": 11, "click": 6457, "like": 36, "dislike": 31, "name": "재영솔루텍", "time": "2018-02-26 11:40"}, {"post_num": 6, "unique_id": 2, "click": 676, "like": 7, "dislike": 0, "name": "유한양행", "time": "2018-02-26 11:40"}, {"post_num": 4, "unique_id": 3, "click": 671, "like": 6, "dislike": 1, "name": "GS", "time": "2018-02-26 11:40"}, {"post_num": 1, "unique_id": 1, "click": 39, "like": 0, "dislike": 1, "name": "비츠로시스", "time": "2018-02-26 11:40"}, {"post_num": 4, "unique_id": 4, "click": 334, "like": 6, "dislike": 4, "name": "에프알텍", "time": "2018-02-26 11:40"}, {"post_num": 1, "unique_id": 1, "click": 27, "like": 0, "dislike": 0, "name": "일신바이오", "time": "2018-02-26 11:40"}, {"post_num": 70, "unique_id": 38, "click": 13402, "like": 117, "dislike": 56, "name": "인디에프", "time": "2018-02-26 11:40"}, {"post_num": 22, "unique_id": 19, "click": 9311, "like": 64, "dislike": 55, "name": "캠시스", "time": "2018-02-26 11:40"}, {"post_num": 1, "unique_id": 1, "click": 107, "like": 0, "dislike": 0, "name": "한세실업", "time": "2018-02-26 11:40"}, {"post_num": 6, "unique_id": 5, "click": 674, "like": 14, "dislike": 2, "name": "네오위즈", "time": "2018-02-26 11:40"}, {"post_num": 1, "unique_id": 1, "click": 98, "like": 0, "dislike": 2, "name": "씨에스윈드", "time": "2018-02-26 11:40"}, {"post_num": 2, "unique_id": 2, "click": 275, "like": 4, "dislike": 1, "name": "미코", "time": "2018-02-26 11:40"}, {"post_num": 59, "unique_id": 23, "click": 7868, "like": 78, "dislike": 54, "name": "골든센츄리", "time": "2018-02-26 11:40"}, {"post_num": 4, "unique_id": 3, "click": 1618, "like": 11, "dislike": 8, "name": "파마리서치프로덕트", "time": "2018-02-26 11:40"}, {"post_num": 14, "unique_id": 13, "click": 4460, "like": 47, "dislike": 40, "name": "액션스퀘어", "time": "2018-02-26 11:40"}, {"post_num": 2, "unique_id": 2, "click": 1020, "like": 7, "dislike": 4, "name": "파트론", "time": "2018-02-26 11:40"}, {"post_num": 1, "unique_id": 1, "click": 304, "like": 2, "dislike": 3, "name": "아이에이", "time": "2018-02-26 11:40"}, {"post_num": 32, "unique_id": 23, "click": 13985, "like": 120, "dislike": 87, "name": "크리스탈", "time": "2018-02-26 11:40"}, {"post_num": 0, "unique_id": 0, "click": 0, "like": 0, "dislike": 0, "name": "한솔제지", "time": "2018-02-26 11:40"}, {"post_num": 8, "unique_id": 7, "click": 8271, "like": 55, "dislike": 14, "name": "비에이치", "time": "2018-02-26 11:40"}, {"post_num": 1, "unique_id": 1, "click": 222, "like": 6, "dislike": 3, "name": "케이프", "time": "2018-02-26 11:40"}, {"post_num": 16, "unique_id": 14, "click": 7244, "like": 49, "dislike": 23, "name": "에이프로젠제약", "time": "2018-02-26 11:40"}, {"post_num": 1, "unique_id": 1, "click": 73, "like": 2, "dislike": 1, "name": "해성산업", "time": "2018-02-26 11:40"}, {"post_num": 7, "unique_id": 5, "click": 1537, "like": 16, "dislike": 17, "name": "일양약품", "time": "2018-02-26 11:40"}, {"post_num": 0, "unique_id": 0, "click": 0, "like": 0, "dislike": 0, "name": "동원개발", "time": "2018-02-26 11:40"}, {"post_num": 37, "unique_id": 24, "click": 13026, "like": 104, "dislike": 72, "name": "위지트", "time": "2018-02-26 11:40"}, {"post_num": 5, "unique_id": 3, "click": 841, "like": 8, "dislike": 8, "name": "바른손이앤에이", "time": "2018-02-26 11:40"}, {"post_num": 29, "unique_id": 21, "click": 8378, "like": 55, "dislike": 30, "name": "라이브플렉스", "time": "2018-02-26 11:40"}, {"post_num": 1, "unique_id": 1, "click": 28, "like": 0, "dislike": 0, "name": "한국캐피탈", "time": "2018-02-26 11:40"}, {"post_num": 2, "unique_id": 2, "click": 155, "like": 1, "dislike": 1, "name": "비츠로테크", "time": "2018-02-26 11:40"}, {"post_num": 1, "unique_id": 1, "click": 89, "like": 1, "dislike": 2, "name": "동아에스티", "time": "2018-02-26 11:40"}, {"post_num": 11, "unique_id": 10, "click": 3957, "like": 31, "dislike": 13, "name": "CJ CGV", "time": "2018-02-26 11:40"}, {"post_num": 0, "unique_id": 0, "click": 0, "like": 0, "dislike": 0, "name": "휴온스글로벌", "time": "2018-02-26 11:40"}, {"post_num": 0, "unique_id": 0, "click": 0, "like": 0, "dislike": 0, "name": "부국철강", "time": "2018-02-26 11:40"}, {"post_num": 6, "unique_id": 5, "click": 811, "like": 7, "dislike": 4, "name": "동국S&C", "time": "2018-02-26 11:40"}, {"post_num": 7, "unique_id": 6, "click": 1542, "like": 7, "dislike": 3, "name": "에스코넥", "time": "2018-02-26 11:40"}, {"post_num": 0, "unique_id": 0, "click": 0, "like": 0, "dislike": 0, "name": "오리온", "time": "2018-02-26 11:40"}, {"post_num": 1, "unique_id": 1, "click": 10, "like": 0, "dislike": 0, "name": "종근당", "time": "2018-02-26 11:40"}, {"post_num": 2, "unique_id": 2, "click": 285, "like": 2, "dislike": 9, "name": "인지컨트롤스", "time": "2018-02-26 11:40"}, {"post_num": 5, "unique_id": 5, "click": 499, "like": 5, "dislike": 5, "name": "영화테크", "time": "2018-02-26 11:40"}, {"post_num": 0, "unique_id": 0, "click": 0, "like": 0, "dislike": 0, "name": "에스트래픽", "time": "2018-02-26 11:40"}, {"post_num": 1, "unique_id": 1, "click": 43, "like": 0, "dislike": 0, "name": "씨엠에스에듀", "time": "2018-02-26 11:40"}, {"post_num": 0, "unique_id": 0, "click": 0, "like": 0, "dislike": 0, "name": "KG ETS", "time": "2018-02-26 11:40"}, {"post_num": 10, "unique_id": 8, "click": 3406, "like": 10, "dislike": 9, "name": "두산인프라코어", "time": "2018-02-26 11:40"}, {"post_num": 32, "unique_id": 25, "click": 8611, "like": 59, "dislike": 41, "name": "이화전기", "time": "2018-02-26 11:40"}, {"post_num": 1, "unique_id": 1, "click": 14, "like": 0, "dislike": 0, "name": "골프존", "time": "2018-02-26 11:40"}, {"post_num": 16, "unique_id": 14, "click": 2348, "like": 30, "dislike": 17, "name": "메가엠디", "time": "2018-02-26 11:40"}, {"post_num": 0, "unique_id": 0, "click": 0, "like": 0, "dislike": 0, "name": "솔브레인", "time": "2018-02-26 11:40"}, {"post_num": 11, "unique_id": 11, "click": 4549, "like": 104, "dislike": 42, "name": "내츄럴엔도텍", "time": "2018-02-26 11:40"}, {"post_num": 0, "unique_id": 0, "click": 0, "like": 0, "dislike": 0, "name": "네오팜", "time": "2018-02-26 11:40"}, {"post_num": 0, "unique_id": 0, "click": 0, "like": 0, "dislike": 0, "name": "케이엠", "time": "2018-02-26 11:40"}, {"post_num": 4, "unique_id": 4, "click": 496, "like": 10, "dislike": 0, "name": "KG모빌리언스", "time": "2018-02-26 11:40"}, {"post_num": 3, "unique_id": 3, "click": 482, "like": 1, "dislike": 2, "name": "민앤지", "time": "2018-02-26 11:40"}, {"post_num": 3, "unique_id": 3, "click": 160, "like": 1, "dislike": 0, "name": "대창스틸", "time": "2018-02-26 11:40"}, {"post_num": 1, "unique_id": 1, "click": 187, "like": 1, "dislike": 2, "name": "DGB금융지주", "time": "2018-02-26 11:40"}, {"post_num": 3, "unique_id": 3, "click": 379, "like": 0, "dislike": 2, "name": "매직마이크로", "time": "2018-02-26 11:40"}, {"post_num": 0, "unique_id": 0, "click": 0, "like": 0, "dislike": 0, "name": "인화정공", "time": "2018-02-26 11:40"}, {"post_num": 2, "unique_id": 2, "click": 381, "like": 3, "dislike": 2, "name": "서플러스글로벌", "time": "2018-02-26 11:40"}, {"post_num": 2, "unique_id": 2, "click": 361, "like": 5, "dislike": 3, "name": "현우산업", "time": "2018-02-26 11:40"}, {"post_num": 6, "unique_id": 6, "click": 1365, "like": 8, "dislike": 12, "name": "파워로직스", "time": "2018-02-26 11:40"}, {"post_num": 11, "unique_id": 8, "click": 3499, "like": 30, "dislike": 21, "name": "신풍제약", "time": "2018-02-26 11:40"}, {"post_num": 8, "unique_id": 7, "click": 928, "like": 15, "dislike": 3, "name": "일동제약", "time": "2018-02-26 11:40"}, {"post_num": 5, "unique_id": 4, "click": 1065, "like": 5, "dislike": 14, "name": "위닉스", "time": "2018-02-26 11:40"}, {"post_num": 10, "unique_id": 9, "click": 2016, "like": 24, "dislike": 16, "name": "엘컴텍", "time": "2018-02-26 11:40"}, {"post_num": 0, "unique_id": 0, "click": 0, "like": 0, "dislike": 0, "name": "삼일", "time": "2018-02-26 11:40"}, {"post_num": 3, "unique_id": 3, "click": 199, "like": 3, "dislike": 2, "name": "이엘케이", "time": "2018-02-26 11:40"}, {"post_num": 1, "unique_id": 1, "click": 71, "like": 2, "dislike": 1, "name": "디비케이", "time": "2018-02-26 11:40"}, {"post_num": 4, "unique_id": 3, "click": 543, "like": 7, "dislike": 2, "name": "코위버", "time": "2018-02-26 11:40"}, {"post_num": 0, "unique_id": 0, "click": 0, "like": 0, "dislike": 0, "name": "정상제이엘에스", "time": "2018-02-26 11:40"}, {"post_num": 1, "unique_id": 1, "click": 73, "like": 2, "dislike": 0, "name": "이건홀딩스", "time": "2018-02-26 11:40"}, {"post_num": 1, "unique_id": 1, "click": 0, "like": 0, "dislike": 0, "name": "파인디지털", "time": "2018-02-26 11:40"}, {"post_num": 0, "unique_id": 0, "click": 0, "like": 0, "dislike": 0, "name": "무학", "time": "2018-02-26 11:40"}, {"post_num": 0, "unique_id": 0, "click": 0, "like": 0, "dislike": 0, "name": "한국종합기술", "time": "2018-02-26 11:40"}, {"post_num": 11, "unique_id": 6, "click": 2509, "like": 49, "dislike": 41, "name": "신성이엔지", "time": "2018-02-26 11:40"}, {"post_num": 11, "unique_id": 10, "click": 2242, "like": 13, "dislike": 1, "name": "에코마케팅", "time": "2018-02-26 11:40"}, {"post_num": 3, "unique_id": 3, "click": 701, "like": 9, "dislike": 0, "name": "엘앤에프", "time": "2018-02-26 11:40"}, {"post_num": 4, "unique_id": 4, "click": 180, "like": 4, "dislike": 0, "name": "티엘아이", "time": "2018-02-26 11:40"}, {"post_num": 5, "unique_id": 4, "click": 1779, "like": 7, "dislike": 16, "name": "삼지전자", "time": "2018-02-26 11:40"}, {"post_num": 15, "unique_id": 12, "click": 3152, "like": 65, "dislike": 39, "name": "와이지엔터테인먼트", "time": "2018-02-26 11:40"}, {"post_num": 0, "unique_id": 0, "click": 0, "like": 0, "dislike": 0, "name": "유신", "time": "2018-02-26 11:40"}, {"post_num": 9, "unique_id": 5, "click": 1404, "like": 13, "dislike": 18, "name": "유진기업", "time": "2018-02-26 11:40"}, {"post_num": 7, "unique_id": 6, "click": 1053, "like": 7, "dislike": 6, "name": "포비스티앤씨", "time": "2018-02-26 11:40"}, {"post_num": 3, "unique_id": 2, "click": 371, "like": 7, "dislike": 2, "name": "아이에스동서", "time": "2018-02-26 11:40"}, {"post_num": 2, "unique_id": 2, "click": 980, "like": 3, "dislike": 13, "name": "현대미포조선", "time": "2018-02-26 11:40"}, {"post_num": 0, "unique_id": 0, "click": 0, "like": 0, "dislike": 0, "name": "대륙제관", "time": "2018-02-26 11:40"}, {"post_num": 0, "unique_id": 0, "click": 0, "like": 0, "dislike": 0, "name": "아세아제지", "time": "2018-02-26 11:40"}, {"post_num": 1, "unique_id": 1, "click": 347, "like": 0, "dislike": 0, "name": "원익IPS", "time": "2018-02-26 11:40"}, {"post_num": 1, "unique_id": 1, "click": 220, "like": 0, "dislike": 0, "name": "한전KPS", "time": "2018-02-26 11:40"}, {"post_num": 2, "unique_id": 2, "click": 383, "like": 3, "dislike": 9, "name": "아비스타", "time": "2018-02-26 11:40"}, {"post_num": 0, "unique_id": 0, "click": 0, "like": 0, "dislike": 0, "name": "우리이티아이", "time": "2018-02-26 11:40"}, {"post_num": 0, "unique_id": 0, "click": 0, "like": 0, "dislike": 0, "name": "이씨에스", "time": "2018-02-26 11:40"}, {"post_num": 2, "unique_id": 2, "click": 84, "like": 2, "dislike": 1, "name": "메타바이오메드", "time": "2018-02-26 11:40"}, {"post_num": 3, "unique_id": 3, "click": 746, "like": 5, "dislike": 4, "name": "유진로봇", "time": "2018-02-26 11:40"}, {"post_num": 4, "unique_id": 4, "click": 734, "like": 4, "dislike": 1, "name": "이니텍", "time": "2018-02-26 11:40"}, {"post_num": 0, "unique_id": 0, "click": 0, "like": 0, "dislike": 0, "name": "YTN", "time": "2018-02-26 11:40"}, {"post_num": 1, "unique_id": 1, "click": 149, "like": 1, "dislike": 0, "name": "덴티움", "time": "2018-02-26 11:40"}, {"post_num": 1, "unique_id": 1, "click": 93, "like": 0, "dislike": 0, "name": "제주항공", "time": "2018-02-26 11:40"}, {"post_num": 0, "unique_id": 0, "click": 0, "like": 0, "dislike": 0, "name": "네오오토", "time": "2018-02-26 11:40"}, {"post_num": 0, "unique_id": 0, "click": 0, "like": 0, "dislike": 0, "name": "스타플렉스", "time": "2018-02-26 11:40"}, {"post_num": 0, "unique_id": 0, "click": 0, "like": 0, "dislike": 0, "name": "원림", "time": "2018-02-26 11:40"}, {"post_num": 1, "unique_id": 1, "click": 127, "like": 1, "dislike": 0, "name": "빙그레", "time": "2018-02-26 11:40"}, {"post_num": 12, "unique_id": 8, "click": 1961, "like": 16, "dislike": 6, "name": "티웨이홀딩스", "time": "2018-02-26 11:40"}, {"post_num": 33, "unique_id": 11, "click": 6910, "like": 86, "dislike": 16, "name": "대한항공", "time": "2018-02-26 11:40"}, {"post_num": 2, "unique_id": 1, "click": 48, "like": 1, "dislike": 0, "name": "TCC동양", "time": "2018-02-26 11:40"}, {"post_num": 0, "unique_id": 0, "click": 0, "like": 0, "dislike": 0, "name": "제일연마", "time": "2018-02-26 11:40"}, {"post_num": 0, "unique_id": 0, "click": 0, "like": 0, "dislike": 0, "name": "화천기공", "time": "2018-02-26 11:40"}, {"post_num": 9, "unique_id": 9, "click": 958, "like": 11, "dislike": 2, "name": "글로벌에스엠", "time": "2018-02-26 11:40"}, {"post_num": 0, "unique_id": 0, "click": 0, "like": 0, "dislike": 0, "name": "쿠쿠홈시스", "time": "2018-02-26 11:40"}, {"post_num": 1, "unique_id": 1, "click": 76, "like": 0, "dislike": 0, "name": "텔코웨어", "time": "2018-02-26 11:40"}, {"post_num": 0, "unique_id": 0, "click": 0, "like": 0, "dislike": 0, "name": "YW", "time": "2018-02-26 11:40"}, {"post_num": 0, "unique_id": 0, "click": 0, "like": 0, "dislike": 0, "name": "서연전자", "time": "2018-02-26 11:40"}, {"post_num": 4, "unique_id": 4, "click": 1828, "like": 9, "dislike": 11, "name": "우리종금", "time": "2018-02-26 11:40"}, {"post_num": 6, "unique_id": 6, "click": 1901, "like": 21, "dislike": 8, "name": "영진약품", "time": "2018-02-26 11:40"}, {"post_num": 1, "unique_id": 1, "click": 246, "like": 4, "dislike": 3, "name": "컬러레이", "time": "2018-02-26 11:40"}, {"post_num": 1, "unique_id": 1, "click": 235, "like": 3, "dislike": 2, "name": "오가닉티코스메틱", "time": "2018-02-26 11:40"}, {"post_num": 5, "unique_id": 2, "click": 479, "like": 2, "dislike": 4, "name": "씨케이에이치", "time": "2018-02-26 11:40"}, {"post_num": 0, "unique_id": 0, "click": 0, "like": 0, "dislike": 0, "name": "서연이화", "time": "2018-02-26 11:40"}, {"post_num": 0, "unique_id": 0, "click": 0, "like": 0, "dislike": 0, "name": "LG하우시스", "time": "2018-02-26 11:40"}, {"post_num": 23, "unique_id": 18, "click": 9146, "like": 72, "dislike": 56, "name": "녹십자셀", "time": "2018-02-26 11:40"}, {"post_num": 0, "unique_id": 0, "click": 0, "like": 0, "dislike": 0, "name": "삼성증권", "time": "2018-02-26 11:40"}, {"post_num": 0, "unique_id": 0, "click": 0, "like": 0, "dislike": 0, "name": "영풍제지", "time": "2018-02-26 11:40"}, {"post_num": 0, "unique_id": 0, "click": 0, "like": 0, "dislike": 0, "name": "크리스탈신소재", "time": "2018-02-26 11:40"}, {"post_num": 0, "unique_id": 0, "click": 0, "like": 0, "dislike": 0, "name": "디알텍", "time": "2018-02-26 11:40"}, {"post_num": 2, "unique_id": 2, "click": 564, "like": 3, "dislike": 1, "name": "에스티팜", "time": "2018-02-26 11:40"}, {"post_num": 1, "unique_id": 1, "click": 514, "like": 4, "dislike": 1, "name": "CJ E&M", "time": "2018-02-26 11:40"}, {"post_num": 0, "unique_id": 0, "click": 0, "like": 0, "dislike": 0, "name": "코프라", "time": "2018-02-26 11:40"}, {"post_num": 1, "unique_id": 1, "click": 68, "like": 0, "dislike": 0, "name": "삼진엘앤디", "time": "2018-02-26 11:40"}, {"post_num": 2, "unique_id": 2, "click": 521, "like": 5, "dislike": 6, "name": "솔고바이오", "time": "2018-02-26 11:40"}, {"post_num": 12, "unique_id": 10, "click": 3222, "like": 25, "dislike": 28, "name": "에스엠", "time": "2018-02-26 11:40"}, {"post_num": 1, "unique_id": 1, "click": 55, "like": 0, "dislike": 0, "name": "대양제지", "time": "2018-02-26 11:40"}, {"post_num": 2, "unique_id": 2, "click": 392, "like": 6, "dislike": 0, "name": "진원생명과학", "time": "2018-02-26 11:40"}, {"post_num": 14, "unique_id": 11, "click": 2390, "like": 14, "dislike": 10, "name": "휠라코리아", "time": "2018-02-26 11:40"}, {"post_num": 1, "unique_id": 1, "click": 88, "like": 0, "dislike": 0, "name": "한글과컴퓨터", "time": "2018-02-26 11:40"}, {"post_num": 1, "unique_id": 1, "click": 567, "like": 8, "dislike": 4, "name": "일진디스플", "time": "2018-02-26 11:40"}, {"post_num": 1, "unique_id": 1, "click": 64, "like": 0, "dislike": 0, "name": "고려아연", "time": "2018-02-26 11:40"}, {"post_num": 2, "unique_id": 2, "click": 592, "like": 5, "dislike": 0, "name": "NH투자증권", "time": "2018-02-26 11:40"}, {"post_num": 5, "unique_id": 5, "click": 467, "like": 4, "dislike": 1, "name": "한국정보인증", "time": "2018-02-26 11:40"}, {"post_num": 7, "unique_id": 7, "click": 3508, "like": 13, "dislike": 5, "name": "서울반도체", "time": "2018-02-26 11:40"}, {"post_num": 0, "unique_id": 0, "click": 0, "like": 0, "dislike": 0, "name": "에스원", "time": "2018-02-26 11:40"}, {"post_num": 5, "unique_id": 4, "click": 1136, "like": 7, "dislike": 1, "name": "현대위아", "time": "2018-02-26 11:40"}, {"post_num": 11, "unique_id": 7, "click": 4598, "like": 30, "dislike": 24, "name": "대한광통신", "time": "2018-02-26 11:40"}, {"post_num": 1, "unique_id": 1, "click": 63, "like": 0, "dislike": 0, "name": "경동나비엔", "time": "2018-02-26 11:40"}]